prettymaps/__init__.py
prettymaps/draw.py
prettymaps/fetch.py
prettymaps/utils.py
prettymaps/presets/abraca-redencao.json
prettymaps/presets/barcelona-plotter.json
prettymaps/presets/barcelona.json
prettymaps/presets/cb-bf-f.json
prettymaps/presets/default.json
prettymaps/presets/heerhugowaard.json
prettymaps/presets/macao.json
prettymaps/presets/minimal.json
prettymaps/presets/plotter.json
prettymaps/presets/tijuca.json
prettymaps-1.4.2.dist-info/LICENSE
prettymaps-1.4.2.dist-info/METADATA
prettymaps-1.4.2.dist-info/WHEEL
prettymaps-1.4.2.dist-info/top_level.txt
prettymaps-1.4.2.dist-info/RECORD
