Metadata-Version: 2.2
Name: prettymaps
Version: 1.4.2
Summary: A simple python library to draw pretty maps from OpenStreetMap data
Home-page: https://github.com/marceloprates/prettymaps
Author: Marcelo Prates
Author-email: marceloorp@gmail.com
License: MIT License
Classifier: Intended Audience :: Science/Research
Requires-Python: >=3.11
License-File: LICENSE
Requires-Dist: numpy<1.25,>=1.20
Requires-Dist: matplotlib>=3.9.0
Requires-Dist: shapely>=2.0.0
Requires-Dist: osmnx<2.0,>=1.9.3
Requires-Dist: ipykernel>=6.29.5
Requires-Dist: rasterio>=1.4.3
Requires-Dist: rioxarray>=0.18.2
Requires-Dist: opencv-python>=4.11.0.86
Requires-Dist: scikit-image>=0.25.2
Requires-Dist: vsketch>=1.0.0
Requires-Dist: thefuzz>=0.22.1
Requires-Dist: elevation>=1.1.3
Requires-Dist: streamlit>=1.42.2
Requires-Dist: tqdm>=4.67.1
Requires-Dist: scikit-learn>=1.6.1
Dynamic: author
Dynamic: author-email
Dynamic: classifier
Dynamic: description
Dynamic: description-content-type
Dynamic: home-page
Dynamic: license
Dynamic: requires-dist
Dynamic: requires-python
Dynamic: summary
